{"cameraMode":{"drawMode":0,"name":"Shaded","section":"Shading Mode"},"sceneLighting":true,"audioPlay":false,"sceneViewState":{"showFog":true,"showMaterialUpdate":false,"showSkybox":true,"showFlares":true,"showImageEffects":true,"showParticleSystems":true},"in2DMode":false,"pivot":{"x":9.569425582885743,"y":2.364431858062744,"z":17.67287826538086},"rotation":{"x":0.09606319665908814,"y":-0.5142043828964233,"z":0.05809325352311134,"w":0.8502888679504395},"size":11.931282043457032,"orthographic":false}